pybacktestchain_gui/__init__.py
pybacktestchain_gui/main.ipynb
pybacktestchain_gui/pybacktestchain_gui.py
pybacktestchain_gui/strategies.py
pybacktestchain_gui/utils.py
pybacktestchain_gui-0.0.0.dist-info/LICENSE
pybacktestchain_gui-0.0.0.dist-info/METADATA
pybacktestchain_gui-0.0.0.dist-info/WHEEL
pybacktestchain_gui-0.0.0.dist-info/RECORD
