Metadata-Version: 2.3
Name: pybacktestchain_gui
Version: 0.0.0
Summary: A nice GUI addition to the pybacktestchain module, project for M2 203 python course
License: MIT
Author: Faune Blanchard
Requires-Python: >=3.11,<4.0
Classifier: License :: OSI Approved :: MIT License
Classifier: Programming Language :: Python :: 3
Classifier: Programming Language :: Python :: 3.11
Classifier: Programming Language :: Python :: 3.12
Classifier: Programming Language :: Python :: 3.13
Requires-Dist: dash (>=2.18.2,<3.0.0)
Requires-Dist: dash-bootstrap-components (>=1.6.0,<2.0.0)
Requires-Dist: numba (>=0.60.0,<0.61.0)
Requires-Dist: polars (>=1.19.0,<2.0.0)
Requires-Dist: pyarrow (>=19.0.0,<20.0.0)
Requires-Dist: pybacktestchain (>=0.2.1,<0.3.0)
